<annotation>
	<folder>P3_seoyoung</folder>
	<filename>0077.jpg</filename>
	<path>C:\Users\IIRC\Desktop\P3_assigned images\P3_train\P3_seoyoung\0077.jpg</path>
	<source>
		<database>Unknown</database>
	</source>
	<size>
		<width>1280</width>
		<height>960</height>
		<depth>3</depth>
	</size>
	<segmented>0</segmented>
	<object>
		<name>medium-spread</name>
		<pose>Unspecified</pose>
		<truncated>0</truncated>
		<difficult>0</difficult>
		<bndbox>
			<xmin>170</xmin>
			<ymin>365</ymin>
			<xmax>335</xmax>
			<ymax>512</ymax>
		</bndbox>
	</object>
	<object>
		<name>small-spread</name>
		<pose>Unspecified</pose>
		<truncated>0</truncated>
		<difficult>0</difficult>
		<bndbox>
			<xmin>340</xmin>
			<ymin>304</ymin>
			<xmax>435</xmax>
			<ymax>413</ymax>
		</bndbox>
	</object>
	<object>
		<name>small-polygonal</name>
		<pose>Unspecified</pose>
		<truncated>0</truncated>
		<difficult>0</difficult>
		<bndbox>
			<xmin>184</xmin>
			<ymin>612</ymin>
			<xmax>304</xmax>
			<ymax>693</ymax>
		</bndbox>
	</object>
	<object>
		<name>small-polygonal</name>
		<pose>Unspecified</pose>
		<truncated>0</truncated>
		<difficult>0</difficult>
		<bndbox>
			<xmin>447</xmin>
			<ymin>511</ymin>
			<xmax>527</xmax>
			<ymax>645</ymax>
		</bndbox>
	</object>
	<object>
		<name>small-spread</name>
		<pose>Unspecified</pose>
		<truncated>0</truncated>
		<difficult>0</difficult>
		<bndbox>
			<xmin>291</xmin>
			<ymin>737</ymin>
			<xmax>399</xmax>
			<ymax>794</ymax>
		</bndbox>
	</object>
	<object>
		<name>medium-spread</name>
		<pose>Unspecified</pose>
		<truncated>0</truncated>
		<difficult>0</difficult>
		<bndbox>
			<xmin>710</xmin>
			<ymin>190</ymin>
			<xmax>860</xmax>
			<ymax>339</ymax>
		</bndbox>
	</object>
	<object>
		<name>medium-polygonal</name>
		<pose>Unspecified</pose>
		<truncated>0</truncated>
		<difficult>0</difficult>
		<bndbox>
			<xmin>462</xmin>
			<ymin>47</ymin>
			<xmax>647</xmax>
			<ymax>216</ymax>
		</bndbox>
	</object>
	<object>
		<name>medium-spread</name>
		<pose>Unspecified</pose>
		<truncated>0</truncated>
		<difficult>0</difficult>
		<bndbox>
			<xmin>423</xmin>
			<ymin>257</ymin>
			<xmax>591</xmax>
			<ymax>455</ymax>
		</bndbox>
	</object>
	<object>
		<name>medium-spread</name>
		<pose>Unspecified</pose>
		<truncated>0</truncated>
		<difficult>0</difficult>
		<bndbox>
			<xmin>540</xmin>
			<ymin>609</ymin>
			<xmax>737</xmax>
			<ymax>777</ymax>
		</bndbox>
	</object>
	<object>
		<name>dividing</name>
		<pose>Unspecified</pose>
		<truncated>0</truncated>
		<difficult>0</difficult>
		<bndbox>
			<xmin>554</xmin>
			<ymin>335</ymin>
			<xmax>778</xmax>
			<ymax>533</ymax>
		</bndbox>
	</object>
	<object>
		<name>medium-spread</name>
		<pose>Unspecified</pose>
		<truncated>0</truncated>
		<difficult>0</difficult>
		<bndbox>
			<xmin>405</xmin>
			<ymin>255</ymin>
			<xmax>601</xmax>
			<ymax>440</ymax>
		</bndbox>
	</object>
	<object>
		<name>medium-spread</name>
		<pose>Unspecified</pose>
		<truncated>0</truncated>
		<difficult>0</difficult>
		<bndbox>
			<xmin>808</xmin>
			<ymin>370</ymin>
			<xmax>999</xmax>
			<ymax>523</ymax>
		</bndbox>
	</object>
	<object>
		<name>medium-polygonal</name>
		<pose>Unspecified</pose>
		<truncated>0</truncated>
		<difficult>0</difficult>
		<bndbox>
			<xmin>366</xmin>
			<ymin>528</ymin>
			<xmax>534</xmax>
			<ymax>655</ymax>
		</bndbox>
	</object>
	<object>
		<name>medium-spread</name>
		<pose>Unspecified</pose>
		<truncated>0</truncated>
		<difficult>0</difficult>
		<bndbox>
			<xmin>735</xmin>
			<ymin>677</ymin>
			<xmax>898</xmax>
			<ymax>904</ymax>
		</bndbox>
	</object>
	<object>
		<name>small-polygonal</name>
		<pose>Unspecified</pose>
		<truncated>0</truncated>
		<difficult>0</difficult>
		<bndbox>
			<xmin>837</xmin>
			<ymin>679</ymin>
			<xmax>905</xmax>
			<ymax>768</ymax>
		</bndbox>
	</object>
	<object>
		<name>medium-polygonal</name>
		<pose>Unspecified</pose>
		<truncated>0</truncated>
		<difficult>0</difficult>
		<bndbox>
			<xmin>834</xmin>
			<ymin>560</ymin>
			<xmax>979</xmax>
			<ymax>691</ymax>
		</bndbox>
	</object>
	<object>
		<name>medium-spread</name>
		<pose>Unspecified</pose>
		<truncated>0</truncated>
		<difficult>0</difficult>
		<bndbox>
			<xmin>864</xmin>
			<ymin>231</ymin>
			<xmax>1033</xmax>
			<ymax>407</ymax>
		</bndbox>
	</object>
	<object>
		<name>medium-polygonal</name>
		<pose>Unspecified</pose>
		<truncated>0</truncated>
		<difficult>0</difficult>
		<bndbox>
			<xmin>935</xmin>
			<ymin>72</ymin>
			<xmax>1142</xmax>
			<ymax>206</ymax>
		</bndbox>
	</object>
	<object>
		<name>small-spread</name>
		<pose>Unspecified</pose>
		<truncated>1</truncated>
		<difficult>0</difficult>
		<bndbox>
			<xmin>996</xmin>
			<ymin>1</ymin>
			<xmax>1102</xmax>
			<ymax>91</ymax>
		</bndbox>
	</object>
</annotation>
