<annotation>
	<folder>P3_eunah</folder>
	<filename>0170.jpg</filename>
	<path>C:\Users\user\Desktop\Rawdata_rbMSC\test\P3_eunah\0170.jpg</path>
	<source>
		<database>Unknown</database>
	</source>
	<size>
		<width>1280</width>
		<height>960</height>
		<depth>3</depth>
	</size>
	<segmented>0</segmented>
	<object>
		<name>large-spread</name>
		<pose>Unspecified</pose>
		<truncated>0</truncated>
		<difficult>0</difficult>
		<bndbox>
			<xmin>472</xmin>
			<ymin>359</ymin>
			<xmax>730</xmax>
			<ymax>598</ymax>
		</bndbox>
	</object>
	<object>
		<name>dividing</name>
		<pose>Unspecified</pose>
		<truncated>0</truncated>
		<difficult>0</difficult>
		<bndbox>
			<xmin>699</xmin>
			<ymin>454</ymin>
			<xmax>754</xmax>
			<ymax>577</ymax>
		</bndbox>
	</object>
	<object>
		<name>medium-spread</name>
		<pose>Unspecified</pose>
		<truncated>0</truncated>
		<difficult>0</difficult>
		<bndbox>
			<xmin>536</xmin>
			<ymin>639</ymin>
			<xmax>668</xmax>
			<ymax>818</ymax>
		</bndbox>
	</object>
	<object>
		<name>medium-spread</name>
		<pose>Unspecified</pose>
		<truncated>0</truncated>
		<difficult>0</difficult>
		<bndbox>
			<xmin>304</xmin>
			<ymin>503</ymin>
			<xmax>474</xmax>
			<ymax>689</ymax>
		</bndbox>
	</object>
	<object>
		<name>medium-spread</name>
		<pose>Unspecified</pose>
		<truncated>0</truncated>
		<difficult>0</difficult>
		<bndbox>
			<xmin>202</xmin>
			<ymin>528</ymin>
			<xmax>330</xmax>
			<ymax>625</ymax>
		</bndbox>
	</object>
	<object>
		<name>large-spread</name>
		<pose>Unspecified</pose>
		<truncated>0</truncated>
		<difficult>0</difficult>
		<bndbox>
			<xmin>4</xmin>
			<ymin>585</ymin>
			<xmax>157</xmax>
			<ymax>928</ymax>
		</bndbox>
	</object>
	<object>
		<name>large-spread</name>
		<pose>Unspecified</pose>
		<truncated>0</truncated>
		<difficult>0</difficult>
		<bndbox>
			<xmin>679</xmin>
			<ymin>132</ymin>
			<xmax>981</xmax>
			<ymax>293</ymax>
		</bndbox>
	</object>
</annotation>
