<annotation>
	<folder>P2_eunah</folder>
	<filename>0043.jpg</filename>
	<path>C:\Users\user\Desktop\Rawdata_rbMSC\train\P2_eunah\0043.jpg</path>
	<source>
		<database>Unknown</database>
	</source>
	<size>
		<width>1280</width>
		<height>960</height>
		<depth>3</depth>
	</size>
	<segmented>0</segmented>
	<object>
		<name>spindle</name>
		<pose>Unspecified</pose>
		<truncated>0</truncated>
		<difficult>0</difficult>
		<bndbox>
			<xmin>195</xmin>
			<ymin>424</ymin>
			<xmax>354</xmax>
			<ymax>469</ymax>
		</bndbox>
	</object>
	<object>
		<name>small-spread</name>
		<pose>Unspecified</pose>
		<truncated>0</truncated>
		<difficult>0</difficult>
		<bndbox>
			<xmin>534</xmin>
			<ymin>360</ymin>
			<xmax>616</xmax>
			<ymax>425</ymax>
		</bndbox>
	</object>
	<object>
		<name>small-polygonal</name>
		<pose>Unspecified</pose>
		<truncated>0</truncated>
		<difficult>0</difficult>
		<bndbox>
			<xmin>120</xmin>
			<ymin>307</ymin>
			<xmax>208</xmax>
			<ymax>433</ymax>
		</bndbox>
	</object>
	<object>
		<name>dividing</name>
		<pose>Unspecified</pose>
		<truncated>0</truncated>
		<difficult>0</difficult>
		<bndbox>
			<xmin>141</xmin>
			<ymin>646</ymin>
			<xmax>434</xmax>
			<ymax>865</ymax>
		</bndbox>
	</object>
	<object>
		<name>small-polygonal</name>
		<pose>Unspecified</pose>
		<truncated>0</truncated>
		<difficult>0</difficult>
		<bndbox>
			<xmin>525</xmin>
			<ymin>679</ymin>
			<xmax>663</xmax>
			<ymax>740</ymax>
		</bndbox>
	</object>
	<object>
		<name>small-polygonal</name>
		<pose>Unspecified</pose>
		<truncated>0</truncated>
		<difficult>0</difficult>
		<bndbox>
			<xmin>608</xmin>
			<ymin>762</ymin>
			<xmax>723</xmax>
			<ymax>867</ymax>
		</bndbox>
	</object>
	<object>
		<name>small-spread</name>
		<pose>Unspecified</pose>
		<truncated>0</truncated>
		<difficult>0</difficult>
		<bndbox>
			<xmin>247</xmin>
			<ymin>228</ymin>
			<xmax>377</xmax>
			<ymax>332</ymax>
		</bndbox>
	</object>
	<object>
		<name>medium-polygonal</name>
		<pose>Unspecified</pose>
		<truncated>1</truncated>
		<difficult>0</difficult>
		<bndbox>
			<xmin>227</xmin>
			<ymin>1</ymin>
			<xmax>370</xmax>
			<ymax>171</ymax>
		</bndbox>
	</object>
</annotation>
