<annotation>
	<folder>P1</folder>
	<filename>0100.jpg</filename>
	<path>C:\Users\user\Temp\newlabel\P1\0100.jpg</path>
	<source>
		<database>Unknown</database>
	</source>
	<size>
		<width>1280</width>
		<height>960</height>
		<depth>3</depth>
	</size>
	<segmented>0</segmented>
	<object>
		<name>spread</name>
		<pose>Unspecified</pose>
		<truncated>0</truncated>
		<difficult>0</difficult>
		<bndbox>
			<xmin>88</xmin>
			<ymin>404</ymin>
			<xmax>261</xmax>
			<ymax>516</ymax>
		</bndbox>
	</object>
	<object>
		<name>spread</name>
		<pose>Unspecified</pose>
		<truncated>0</truncated>
		<difficult>0</difficult>
		<bndbox>
			<xmin>261</xmin>
			<ymin>516</ymin>
			<xmax>384</xmax>
			<ymax>704</ymax>
		</bndbox>
	</object>
	<object>
		<name>spread</name>
		<pose>Unspecified</pose>
		<truncated>0</truncated>
		<difficult>0</difficult>
		<bndbox>
			<xmin>380</xmin>
			<ymin>645</ymin>
			<xmax>520</xmax>
			<ymax>791</ymax>
		</bndbox>
	</object>
	<object>
		<name>spread</name>
		<pose>Unspecified</pose>
		<truncated>0</truncated>
		<difficult>0</difficult>
		<bndbox>
			<xmin>623</xmin>
			<ymin>589</ymin>
			<xmax>762</xmax>
			<ymax>810</ymax>
		</bndbox>
	</object>
	<object>
		<name>spread</name>
		<pose>Unspecified</pose>
		<truncated>0</truncated>
		<difficult>0</difficult>
		<bndbox>
			<xmin>226</xmin>
			<ymin>857</ymin>
			<xmax>461</xmax>
			<ymax>958</ymax>
		</bndbox>
	</object>
	<object>
		<name>spread</name>
		<pose>Unspecified</pose>
		<truncated>0</truncated>
		<difficult>0</difficult>
		<bndbox>
			<xmin>892</xmin>
			<ymin>184</ymin>
			<xmax>1018</xmax>
			<ymax>353</ymax>
		</bndbox>
	</object>
	<object>
		<name>dividing</name>
		<pose>Unspecified</pose>
		<truncated>0</truncated>
		<difficult>0</difficult>
		<bndbox>
			<xmin>822</xmin>
			<ymin>403</ymin>
			<xmax>956</xmax>
			<ymax>576</ymax>
		</bndbox>
	</object>
	<object>
		<name>polygonal</name>
		<pose>Unspecified</pose>
		<truncated>0</truncated>
		<difficult>0</difficult>
		<bndbox>
			<xmin>209</xmin>
			<ymin>7</ymin>
			<xmax>312</xmax>
			<ymax>117</ymax>
		</bndbox>
	</object>
	<object>
		<name>spread</name>
		<pose>Unspecified</pose>
		<truncated>0</truncated>
		<difficult>0</difficult>
		<bndbox>
			<xmin>1135</xmin>
			<ymin>663</ymin>
			<xmax>1275</xmax>
			<ymax>822</ymax>
		</bndbox>
	</object>
</annotation>
