<annotation>
	<folder>P1</folder>
	<filename>0069.jpg</filename>
	<path>C:\Users\user\Temp\newlabel\P1\0069.jpg</path>
	<source>
		<database>Unknown</database>
	</source>
	<size>
		<width>1280</width>
		<height>960</height>
		<depth>3</depth>
	</size>
	<segmented>0</segmented>
	<object>
		<name>polygonal</name>
		<pose>Unspecified</pose>
		<truncated>0</truncated>
		<difficult>0</difficult>
		<bndbox>
			<xmin>352</xmin>
			<ymin>368</ymin>
			<xmax>437</xmax>
			<ymax>508</ymax>
		</bndbox>
	</object>
	<object>
		<name>spread</name>
		<pose>Unspecified</pose>
		<truncated>0</truncated>
		<difficult>0</difficult>
		<bndbox>
			<xmin>543</xmin>
			<ymin>785</ymin>
			<xmax>665</xmax>
			<ymax>903</ymax>
		</bndbox>
	</object>
	<object>
		<name>spread</name>
		<pose>Unspecified</pose>
		<truncated>0</truncated>
		<difficult>0</difficult>
		<bndbox>
			<xmin>953</xmin>
			<ymin>401</ymin>
			<xmax>1075</xmax>
			<ymax>519</ymax>
		</bndbox>
	</object>
	<object>
		<name>dividing</name>
		<pose>Unspecified</pose>
		<truncated>0</truncated>
		<difficult>0</difficult>
		<bndbox>
			<xmin>943</xmin>
			<ymin>139</ymin>
			<xmax>1137</xmax>
			<ymax>290</ymax>
		</bndbox>
	</object>
</annotation>
