<annotation>
	<folder>P1</folder>
	<filename>0125.jpg</filename>
	<path>C:\Users\Jisoo_Lee\Desktop\train\P1\0125.jpg</path>
	<source>
		<database>Unknown</database>
	</source>
	<size>
		<width>1280</width>
		<height>960</height>
		<depth>3</depth>
	</size>
	<segmented>0</segmented>
	<object>
		<name>Polygonal</name>
		<pose>Unspecified</pose>
		<truncated>0</truncated>
		<difficult>0</difficult>
		<bndbox>
			<xmin>928</xmin>
			<ymin>411</ymin>
			<xmax>1029</xmax>
			<ymax>536</ymax>
		</bndbox>
	</object>
	<object>
		<name>Ignore</name>
		<pose>Unspecified</pose>
		<truncated>0</truncated>
		<difficult>0</difficult>
		<bndbox>
			<xmin>912</xmin>
			<ymin>246</ymin>
			<xmax>1011</xmax>
			<ymax>363</ymax>
		</bndbox>
	</object>
	<object>
		<name>Polygonal</name>
		<pose>Unspecified</pose>
		<truncated>0</truncated>
		<difficult>0</difficult>
		<bndbox>
			<xmin>942</xmin>
			<ymin>97</ymin>
			<xmax>1033</xmax>
			<ymax>240</ymax>
		</bndbox>
	</object>
	<object>
		<name>Polygonal</name>
		<pose>Unspecified</pose>
		<truncated>0</truncated>
		<difficult>0</difficult>
		<bndbox>
			<xmin>391</xmin>
			<ymin>727</ymin>
			<xmax>450</xmax>
			<ymax>880</ymax>
		</bndbox>
	</object>
	<object>
		<name>Ignore</name>
		<pose>Unspecified</pose>
		<truncated>0</truncated>
		<difficult>0</difficult>
		<bndbox>
			<xmin>544</xmin>
			<ymin>548</ymin>
			<xmax>627</xmax>
			<ymax>649</ymax>
		</bndbox>
	</object>
	<object>
		<name>Ignore</name>
		<pose>Unspecified</pose>
		<truncated>0</truncated>
		<difficult>0</difficult>
		<bndbox>
			<xmin>470</xmin>
			<ymin>686</ymin>
			<xmax>602</xmax>
			<ymax>820</ymax>
		</bndbox>
	</object>
	<object>
		<name>Ignore</name>
		<pose>Unspecified</pose>
		<truncated>0</truncated>
		<difficult>0</difficult>
		<bndbox>
			<xmin>911</xmin>
			<ymin>616</ymin>
			<xmax>1102</xmax>
			<ymax>859</ymax>
		</bndbox>
	</object>
	<object>
		<name>Spread</name>
		<pose>Unspecified</pose>
		<truncated>0</truncated>
		<difficult>0</difficult>
		<bndbox>
			<xmin>1101</xmin>
			<ymin>814</ymin>
			<xmax>1209</xmax>
			<ymax>937</ymax>
		</bndbox>
	</object>
	<object>
		<name>Small</name>
		<pose>Unspecified</pose>
		<truncated>0</truncated>
		<difficult>0</difficult>
		<bndbox>
			<xmin>1188</xmin>
			<ymin>181</ymin>
			<xmax>1270</xmax>
			<ymax>268</ymax>
		</bndbox>
	</object>
	<object>
		<name>Polygonal</name>
		<pose>Unspecified</pose>
		<truncated>0</truncated>
		<difficult>0</difficult>
		<bndbox>
			<xmin>422</xmin>
			<ymin>373</ymin>
			<xmax>534</xmax>
			<ymax>427</ymax>
		</bndbox>
	</object>
	<object>
		<name>Spread</name>
		<pose>Unspecified</pose>
		<truncated>0</truncated>
		<difficult>0</difficult>
		<bndbox>
			<xmin>493</xmin>
			<ymin>117</ymin>
			<xmax>687</xmax>
			<ymax>258</ymax>
		</bndbox>
	</object>
</annotation>