<annotation>
	<folder>P2</folder>
	<filename>0043.jpg</filename>
	<path>C:\Users\user\Desktop\Raw_data_seeyourcells\Temp\newlabel\P2\0043.jpg</path>
	<source>
		<database>Unknown</database>
	</source>
	<size>
		<width>1280</width>
		<height>960</height>
		<depth>3</depth>
	</size>
	<segmented>0</segmented>
	<object>
		<name>small</name>
		<pose>Unspecified</pose>
		<truncated>0</truncated>
		<difficult>0</difficult>
		<bndbox>
			<xmin>591</xmin>
			<ymin>766</ymin>
			<xmax>726</xmax>
			<ymax>871</ymax>
		</bndbox>
	</object>
	<object>
		<name>small</name>
		<pose>Unspecified</pose>
		<truncated>0</truncated>
		<difficult>0</difficult>
		<bndbox>
			<xmin>528</xmin>
			<ymin>670</ymin>
			<xmax>662</xmax>
			<ymax>741</ymax>
		</bndbox>
	</object>
	<object>
		<name>small</name>
		<pose>Unspecified</pose>
		<truncated>0</truncated>
		<difficult>0</difficult>
		<bndbox>
			<xmin>633</xmin>
			<ymin>331</ymin>
			<xmax>763</xmax>
			<ymax>427</ymax>
		</bndbox>
	</object>
	<object>
		<name>spindle</name>
		<pose>Unspecified</pose>
		<truncated>0</truncated>
		<difficult>0</difficult>
		<bndbox>
			<xmin>192</xmin>
			<ymin>414</ymin>
			<xmax>350</xmax>
			<ymax>485</ymax>
		</bndbox>
	</object>
	<object>
		<name>polygonal</name>
		<pose>Unspecified</pose>
		<truncated>0</truncated>
		<difficult>0</difficult>
		<bndbox>
			<xmin>117</xmin>
			<ymin>310</ymin>
			<xmax>215</xmax>
			<ymax>456</ymax>
		</bndbox>
	</object>
	<object>
		<name>polygonal</name>
		<pose>Unspecified</pose>
		<truncated>0</truncated>
		<difficult>0</difficult>
		<bndbox>
			<xmin>231</xmin>
			<ymin>2</ymin>
			<xmax>373</xmax>
			<ymax>174</ymax>
		</bndbox>
	</object>
	<object>
		<name>polygonal</name>
		<pose>Unspecified</pose>
		<truncated>0</truncated>
		<difficult>0</difficult>
		<bndbox>
			<xmin>797</xmin>
			<ymin>743</ymin>
			<xmax>898</xmax>
			<ymax>889</ymax>
		</bndbox>
	</object>
</annotation>
