<annotation>
	<folder>P2</folder>
	<filename>0214.jpg</filename>
	<path>C:\Users\user\Desktop\Raw_data_seeyourcells\Temp\newlabel\P2\0214.jpg</path>
	<source>
		<database>Unknown</database>
	</source>
	<size>
		<width>1280</width>
		<height>960</height>
		<depth>3</depth>
	</size>
	<segmented>0</segmented>
	<object>
		<name>polygonal</name>
		<pose>Unspecified</pose>
		<truncated>0</truncated>
		<difficult>0</difficult>
		<bndbox>
			<xmin>779</xmin>
			<ymin>288</ymin>
			<xmax>898</xmax>
			<ymax>409</ymax>
		</bndbox>
	</object>
	<object>
		<name>polygonal</name>
		<pose>Unspecified</pose>
		<truncated>0</truncated>
		<difficult>0</difficult>
		<bndbox>
			<xmin>710</xmin>
			<ymin>377</ymin>
			<xmax>889</xmax>
			<ymax>471</ymax>
		</bndbox>
	</object>
	<object>
		<name>polygonal</name>
		<pose>Unspecified</pose>
		<truncated>0</truncated>
		<difficult>0</difficult>
		<bndbox>
			<xmin>639</xmin>
			<ymin>284</ymin>
			<xmax>717</xmax>
			<ymax>415</ymax>
		</bndbox>
	</object>
</annotation>
